Metadata-Version: 1.1
Name: vega-component
Version: 0.0.1
Summary: A component to render vega specs
Home-page: UNKNOWN
Author: Tom McKenzie <tmckenzie.nz@gmail.com>
Author-email: UNKNOWN
License: UNKNOWN
Platform: UNKNOWN
Classifier: Framework :: Dash
